[{"date": "2006-10-07", "title": "What!? I'm a Tenth-Generation Mafia Boss!?", "type": "Canon", "no": 1}, {"date": "2006-10-14", "title": "The End of the School?!", "type": "Canon", "no": 2}, {"date": "2006-10-21", "title": "Shocking! Cooking With Love and Horror!", "type": "Canon", "no": 3}, {"date": "2006-10-28", "title": "Eek! A Maiden's Heart Can Destroy!", "type": "Canon", "no": 4}, {"date": "2006-11-04", "title": "The Leader of the Disciplinary Committee Kills Time.", "type": "Canon", "no": 5}, {"date": "2006-11-11", "title": "Ni-Hao Gyoza Fist!", "type": "Canon", "no": 6}, {"date": "2006-11-18", "title": "To the Limit! Passionate Brother!", "type": "Canon", "no": 7}, {"date": "2006-11-25", "title": "The Senior Boss Cares About the Family.", "type": "Canon", "no": 8}, {"date": "2006-12-02", "title": "Life-shortening Skullitis", "type": "Canon", "no": 9}, {"date": "2006-12-09", "title": "Gahaha! The Exploding Lunch Box!", "type": "Canon", "no": 10}, {"date": "2006-12-16", "title": "The Gyoza Buns of Love and Death!?", "type": "Canon", "no": 11}, {"date": "2006-12-23", "title": "Master's Training! Strengthening Program", "type": "Canon", "no": 12}, {"date": "2007-01-06", "title": "New Spring! The Hundred Million Yen Contest", "type": "Canon", "no": 13}, {"date": "2007-01-13", "title": "First Date!? Hell's Zoo", "type": "Canon", "no": 14}, {"date": "2007-01-20", "title": "Clash! Survival Snow Battle", "type": "Canon", "no": 15}, {"date": "2007-01-27", "title": "Escape From Death Mountain!", "type": "Canon", "no": 16}, {"date": "2007-02-03", "title": "Don't Make a Noise When You're Hospitalized", "type": "Canon", "no": 17}, {"date": "2007-02-10", "title": "Poisoned Love Chocolates", "type": "Canon", "no": 18}, {"date": "2007-02-17", "title": "100% Accuracy? Ranking Anything", "type": "Canon", "no": 19}, {"date": "2007-02-24", "title": "Sudden Attack", "type": "Canon", "no": 20}, {"date": "2007-03-03", "title": "Wounded Friends", "type": "Canon", "no": 21}, {"date": "2007-03-10", "title": "Unforeseen Evil Influence", "type": "Canon", "no": 22}, {"date": "2007-03-17", "title": "The Final Deathperation Shot", "type": "Canon", "no": 23}, {"date": "2007-03-24", "title": "Fighting Back in Different Ways", "type": "Canon", "no": 24}, {"date": "2007-03-31", "title": "I Want to Win! Moment of Awakening", "type": "Canon", "no": 25}, {"date": "2007-04-07", "title": "The End and From Then On", "type": "Canon", "no": 26}, {"date": "2007-04-14", "title": "Eat Sushi to Celebrate Moving Up a Grade", "type": "Canon", "no": 27}, {"date": "2007-04-21", "title": "No Way! I Killed Him?", "type": "Canon", "no": 28}, {"date": "2007-04-28", "title": "Her Lover is Broccoli?", "type": "Canon", "no": 29}, {"date": "2007-05-05", "title": "Hide and Seek on a Luxury Cruise", "type": "Canon", "no": 30}, {"date": "2007-05-12", "title": "Welcome to Mafia Land", "type": "Canon", "no": 31}, {"date": "2007-05-19", "title": "A Shark Showed Up in the Public Pool", "type": "Canon", "no": 32}, {"date": "2007-05-26", "title": "A Summer Filled With Debt?", "type": "Canon", "no": 33}, {"date": "2007-06-02", "title": "The Varia Arrive", "type": "Canon", "no": 34}, {"date": "2007-06-09", "title": "The Seven Vongola Rings", "type": "Canon", "no": 35}, {"date": "2007-06-16", "title": "Tutors on the Move", "type": "Canon", "no": 36}, {"date": "2007-06-23", "title": "Teacher and Student Together", "type": "Canon", "no": 37}, {"date": "2007-06-30", "title": "The Selfish Baby Cow Vanishes", "type": "Canon", "no": 38}, {"date": "2007-07-07", "title": "The Unseen Enemies' Goal", "type": "Canon", "no": 39}, {"date": "2007-07-14", "title": "The Battle of the Rings Begins!", "type": "Canon", "no": 40}, {"date": "2007-07-21", "title": "The Guardian of the Sun Ring's Feelings", "type": "Canon", "no": 41}, {"date": "2007-07-28", "title": "The Power to Overcome Adversity", "type": "Canon", "no": 42}, {"date": "2007-08-04", "title": "Thunder Strike from Twenty Years Later", "type": "Canon", "no": 43}, {"date": "2007-08-11", "title": "The Stolen Sky Ring", "type": "Canon", "no": 44}, {"date": "2007-08-18", "title": "Raging Storm Battle", "type": "Canon", "no": 45}, {"date": "2007-08-25", "title": "Reason to Fight", "type": "Canon", "no": 46}, {"date": "2007-09-01", "title": "The Strongest, Invincible Style", "type": "Canon", "no": 47}, {"date": "2007-09-08", "title": "Flow of Battle", "type": "Canon", "no": 48}, {"date": "2007-09-15", "title": "Requiem Rain", "type": "Canon", "no": 49}, {"date": "2007-09-22", "title": "The Guardian of the Mist Ring Arrives!?", "type": "Canon", "no": 50}, {"date": "2007-09-29", "title": "Illusion vs. Illusion", "type": "Canon", "no": 51}, {"date": "2007-10-06", "title": "The Truth About the Mist", "type": "Canon", "no": 52}, {"date": "2007-10-13", "title": "A Hint of Uneasiness", "type": "Canon", "no": 53}, {"date": "2007-10-20", "title": "The Cloud Guardian's Rampage", "type": "Canon", "no": 54}, {"date": "2007-10-27", "title": "Determination", "type": "Canon", "no": 55}, {"date": "2007-11-03", "title": "Gokudera's Story", "type": "Filler", "no": 56}, {"date": "2007-11-10", "title": "The Sky Ring Battle Begins!", "type": "Canon", "no": 57}, {"date": "2007-11-17", "title": "Flame of Fury", "type": "Canon", "no": 58}, {"date": "2007-11-24", "title": "Supporters", "type": "Canon", "no": 59}, {"date": "2007-12-01", "title": "Deathperate Zero Point Breakthrough", "type": "Canon", "no": 60}, {"date": "2007-12-08", "title": "Zero Point Breakthrough Revised", "type": "Canon", "no": 61}, {"date": "2007-12-15", "title": "Tactics", "type": "Canon", "no": 62}, {"date": "2007-12-22", "title": "Freezing Flame", "type": "Canon", "no": 63}, {"date": "2008-01-18", "title": "The Truth Behind The Rage", "type": "Canon", "no": 64}, {"date": "2008-01-12", "title": "Conclusion!", "type": "Canon", "no": 65}, {"date": "2008-01-19", "title": "Shivering Ghost", "type": "Canon", "no": 66}, {"date": "2008-01-26", "title": "Vongola-style Open House", "type": "Canon", "no": 67}, {"date": "2008-02-02", "title": "Happy? Wedding", "type": "Canon", "no": 68}, {"date": "2008-02-09", "title": "Crazy Criminal Brother Trio", "type": "Canon", "no": 69}, {"date": "2008-02-16", "title": "The Misfortune of Shoichi Irie", "type": "Canon", "no": 70}, {"date": "2008-02-23", "title": "Fighting Spirit! Absolute Evil Fist", "type": "Canon", "no": 71}, {"date": "2008-03-01", "title": "Expulsion Crisis", "type": "Canon", "no": 72}, {"date": "2008-03-08", "title": "Mother's Day Vongola-style", "type": "Canon", "no": 73}, {"date": "2008-03-15", "title": "The World 10 Years Later", "type": "Canon", "no": 74}, {"date": "2008-03-22", "title": "Secret Base", "type": "Canon", "no": 75}, {"date": "2008-03-29", "title": "Search for the Guardians", "type": "Canon", "no": 76}, {"date": "2008-04-05", "title": "Flame of Resolve", "type": "Canon", "no": 77}, {"date": "2008-04-12", "title": "Clues to The Past", "type": "Canon", "no": 78}, {"date": "2008-04-19", "title": "The First Trial", "type": "Canon", "no": 79}, {"date": "2008-04-26", "title": "Discord", "type": "Canon", "no": 80}, {"date": "2008-05-03", "title": "Combination", "type": "Canon", "no": 81}, {"date": "2008-05-10", "title": "The Strongest Guardian", "type": "Canon", "no": 82}, {"date": "2008-05-17", "title": "Information Divulged", "type": "Canon", "no": 83}, {"date": "2008-05-24", "title": "The Long Road Home", "type": "Canon", "no": 84}, {"date": "2008-05-31", "title": "Where's the Base?", "type": "Canon", "no": 85}, {"date": "2008-06-07", "title": "The Most Terrifying Tutor", "type": "Canon", "no": 86}, {"date": "2008-06-14", "title": "Succession", "type": "Canon", "no": 87}, {"date": "2008-06-21", "title": "7\u00b3 Policy", "type": "Canon", "no": 88}, {"date": "2008-06-28", "title": "Piano of Sorrow", "type": "Canon", "no": 89}, {"date": "2008-07-05", "title": "Gufo di Pioggia", "type": "Canon", "no": 90}, {"date": "2008-07-12", "title": "What You Believe In", "type": "Canon", "no": 91}, {"date": "2008-07-19", "title": "Your Choice", "type": "Canon", "no": 92}, {"date": "2008-07-26", "title": "Level D Security Alert", "type": "Canon", "no": 93}, {"date": "2008-08-02", "title": "Identity Revealed", "type": "Canon", "no": 94}, {"date": "2008-08-09", "title": "Determination", "type": "Canon", "no": 95}, {"date": "2008-08-23", "title": "X BURNER", "type": "Canon", "no": 96}, {"date": "2008-08-30", "title": "The Great Chase", "type": "Filler", "no": 97}, {"date": "2008-09-06", "title": "Declaration of War", "type": "Canon", "no": 98}, {"date": "2008-09-13", "title": "The Final Trial", "type": "Canon", "no": 99}, {"date": "2008-09-20", "title": "The Night Before the Raid", "type": "Canon", "no": 100}, {"date": "2008-09-27", "title": "Night Attack", "type": "Canon", "no": 101}, {"date": "2008-10-04", "title": "Mission Start", "type": "Canon", "no": 102}, {"date": "2008-10-11", "title": "The First Barrier", "type": "Canon", "no": 103}, {"date": "2008-10-18", "title": "Magician of Fate", "type": "Canon", "no": 104}, {"date": "2008-10-25", "title": "Regret", "type": "Canon", "no": 105}, {"date": "2008-11-01", "title": "The Student's Maturation", "type": "Canon", "no": 106}, {"date": "2008-11-08", "title": "Absolute Desperation", "type": "Canon", "no": 107}, {"date": "2008-11-15", "title": "A Man's Box Weapon", "type": "Canon", "no": 108}, {"date": "2008-11-22", "title": "Captive", "type": "Canon", "no": 109}, {"date": "2008-11-29", "title": "The Secret of Merone Base", "type": "Canon", "no": 110}, {"date": "2008-12-06", "title": "The Enemy is Octopus Head", "type": "Canon", "no": 111}, {"date": "2008-12-13", "title": "Boomerang Trap", "type": "Canon", "no": 112}, {"date": "2008-12-20", "title": "Lightning Strikes Again", "type": "Canon", "no": 113}, {"date": "2008-12-27", "title": "The Storm Guardian, Stands", "type": "Canon", "no": 114}, {"date": "2009-01-10", "title": "SISTEMA C.A.I.", "type": "Canon", "no": 115}, {"date": "2009-01-17", "title": "Difference in Resolve", "type": "Canon", "no": 116}, {"date": "2009-01-24", "title": "Storm Fights Back", "type": "Canon", "no": 117}, {"date": "2009-01-31", "title": "The Princess's Conviction", "type": "Canon", "no": 118}, {"date": "2009-02-07", "title": "Interval Between Battles", "type": "Filler", "no": 119}, {"date": "2009-02-14", "title": "Virtual Space", "type": "Canon", "no": 120}, {"date": "2009-02-21", "title": "Two Battles", "type": "Canon", "no": 121}, {"date": "2009-02-28", "title": "The Ultimate Swordsman", "type": "Canon", "no": 122}, {"date": "2009-03-07", "title": "Teachings of the Sword Emperor", "type": "Canon", "no": 123}, {"date": "2009-03-14", "title": "Obstructing Mist", "type": "Canon", "no": 124}, {"date": "2009-03-21", "title": "More Intruders", "type": "Canon", "no": 125}, {"date": "2009-03-28", "title": "The Strongest versus The Strongest", "type": "Canon", "no": 126}, {"date": "2009-04-04", "title": "A Bewitching Flower", "type": "Canon", "no": 127}, {"date": "2009-04-11", "title": "The Head Prefect Comes", "type": "Canon", "no": 128}, {"date": "2009-04-18", "title": "Operation X", "type": "Canon", "no": 129}, {"date": "2009-04-25", "title": "Resolve and Irritation", "type": "Canon", "no": 130}, {"date": "2009-05-02", "title": "Rampage", "type": "Canon", "no": 131}, {"date": "2009-05-09", "title": "Final Block Of Defense", "type": "Canon", "no": 132}, {"date": "2009-05-16", "title": "A Game-Changing Move", "type": "Canon", "no": 133}, {"date": "2009-05-23", "title": "Hell Knight", "type": "Canon", "no": 134}, {"date": "2009-05-30", "title": "Arrival", "type": "Canon", "no": 135}, {"date": "2009-06-06", "title": "Revealed Truth", "type": "Canon", "no": 136}, {"date": "2009-06-13", "title": "Main Battle in Italy", "type": "Canon", "no": 137}, {"date": "2009-06-20", "title": "Twin Princes", "type": "Canon", "no": 138}, {"date": "2009-06-27", "title": "Furious Roar", "type": "Canon", "no": 139}, {"date": "2009-07-04", "title": "Another Sky", "type": "Canon", "no": 140}, {"date": "2009-07-11", "title": "Reunion", "type": "Canon", "no": 141}, {"date": "2009-07-18", "title": "The Strongest Seven", "type": "Filler", "no": 142}, {"date": "2009-07-25", "title": "Trial #1", "type": "Filler", "no": 143}, {"date": "2009-08-01", "title": "The Arcobaleno Seals", "type": "Filler", "no": 144}, {"date": "2009-08-08", "title": "Guardian Showdown! Cloud and Mist", "type": "Filler", "no": 145}, {"date": "2009-08-15", "title": "Box Weapon Prototype", "type": "Filler", "no": 146}, {"date": "2009-08-22", "title": "Catch the Wind", "type": "Filler", "no": 147}, {"date": "2009-08-29", "title": "Two Successors of the Sky", "type": "Filler", "no": 148}, {"date": "2009-09-05", "title": "Reborn's Trial", "type": "Filler", "no": 149}, {"date": "2009-09-12", "title": "A Path is Closed Off", "type": "Filler", "no": 150}, {"date": "2009-09-19", "title": "Once the Rainbow is Complete", "type": "Filler", "no": 151}, {"date": "2009-09-26", "title": "A Boss' Resolve", "type": "Filler", "no": 152}, {"date": "2009-10-03", "title": "The Final Seal", "type": "Filler", "no": 153}, {"date": "2009-10-10", "title": "To the Next Battle", "type": "Canon", "no": 154}, {"date": "2009-10-17", "title": "The Real Six Funeral Wreaths", "type": "Canon", "no": 155}, {"date": "2009-10-24", "title": "Inspiring Allies", "type": "Canon", "no": 156}, {"date": "2009-10-31", "title": "Namimori Holiday", "type": "Canon", "no": 157}, {"date": "2009-11-07", "title": "A Warm Place", "type": "Canon", "no": 158}, {"date": "2009-11-14", "title": "For My Friends", "type": "Canon", "no": 159}, {"date": "2009-11-21", "title": "Gaining Mobility", "type": "Canon", "no": 160}, {"date": "2009-11-28", "title": "Airbike", "type": "Canon", "no": 161}, {"date": "2009-12-05", "title": "The Sky Vongola Box", "type": "Canon", "no": 162}, {"date": "2009-12-12", "title": "Terror! Turmoil on Base", "type": "Canon", "no": 163}, {"date": "2009-12-19", "title": "Vongola Box, Training Begins", "type": "Canon", "no": 164}, {"date": "2009-12-26", "title": "Boycott Declared", "type": "Canon", "no": 165}, {"date": "2010-01-09", "title": "With the Same Heart", "type": "Canon", "no": 166}, {"date": "2010-01-16", "title": "Day of the Battle", "type": "Canon", "no": 167}, {"date": "2010-01-23", "title": "Choice Begins", "type": "Canon", "no": 168}, {"date": "2010-01-30", "title": "Sky Lion: Leone di Cielo ver. Vongola", "type": "Canon", "no": 169}, {"date": "2010-02-06", "title": "Fateful Showdown", "type": "Canon", "no": 170}, {"date": "2010-02-13", "title": "Revenge", "type": "Canon", "no": 171}, {"date": "2010-02-20", "title": "Kikyo's Assault", "type": "Canon", "no": 172}, {"date": "2010-02-27", "title": "Choice Ends", "type": "Canon", "no": 173}, {"date": "2010-03-06", "title": "The Truth about the Future", "type": "Canon", "no": 174}, {"date": "2010-03-13", "title": "Yuni Comes", "type": "Canon", "no": 175}, {"date": "2010-03-20", "title": "Escape", "type": "Canon", "no": 176}, {"date": "2010-03-27", "title": "After the Battle", "type": "Canon", "no": 177}, {"date": "2010-04-03", "title": "The Primo Family Arrives!", "type": "Filler", "no": 178}, {"date": "2010-04-10", "title": "Inheritance Begins", "type": "Filler", "no": 179}, {"date": "2010-04-17", "title": "The Duty of the Rain Guardian", "type": "Filler", "no": 180}, {"date": "2010-04-24", "title": "Furious Bolt of Lightning", "type": "Filler", "no": 181}, {"date": "2010-05-01", "title": "Silent Storm", "type": "Filler", "no": 182}, {"date": "2010-05-08", "title": "Aloof Cloud", "type": "Filler", "no": 183}, {"date": "2010-05-15", "title": "Sunny then Cloudy", "type": "Filler", "no": 184}, {"date": "2010-05-22", "title": "The Trap is Set", "type": "Filler", "no": 185}, {"date": "2010-05-29", "title": "Bewitching Mist", "type": "Filler", "no": 186}, {"date": "2010-06-05", "title": "Memories of Betrayal", "type": "Filler", "no": 187}, {"date": "2010-06-12", "title": "Primo's Will", "type": "Filler", "no": 188}, {"date": "2010-06-19", "title": "The Family's Resolve", "type": "Filler", "no": 189}, {"date": "2010-06-26", "title": "The Real Six Funeral Wreaths Attack!", "type": "Canon", "no": 190}, {"date": "2010-07-03", "title": "Open Carnage Box", "type": "Canon", "no": 191}, {"date": "2010-07-10", "title": "Alaude's Handcuffs", "type": "Canon", "no": 192}, {"date": "2010-07-17", "title": "Daemon Spade's Devil Lens", "type": "Canon", "no": 193}, {"date": "2010-07-24", "title": "The Final Battle Begins", "type": "Canon", "no": 194}, {"date": "2010-07-31", "title": "G's Archery", "type": "Canon", "no": 195}, {"date": "2010-08-07", "title": "Lambo's Shield", "type": "Canon", "no": 196}, {"date": "2010-08-14", "title": "Knuckle's Maximum Break", "type": "Canon", "no": 197}, {"date": "2010-08-21", "title": "The Last Real Funeral Wreath", "type": "Canon", "no": 198}, {"date": "2010-08-28", "title": "Ghost Awakens", "type": "Canon", "no": 199}, {"date": "2010-09-04", "title": "Sky Full of Desire", "type": "Canon", "no": 200}, {"date": "2010-09-18", "title": "Sea. Clam. Rainbow.", "type": "Canon", "no": 202}, {"date": "2010-09-25", "title": "To a New Future", "type": "Canon", "no": 203}]